mopidy_mopify/__init__.py
mopidy_mopify/ext.conf
mopidy_mopify/static/index.html
mopidy_mopify/static/js/playlists.js
mopidy_mopify/static/js/player.js
mopidy_mopify/static/js/radio.js
mopidy_mopify/static/js/keyboard.js
mopidy_mopify/static/js/search.js
mopidy_mopify/static/js/metapagebuilder.js
mopidy_mopify/static/js/core.js
mopidy_mopify/static/js/browse.js
mopidy_mopify/static/js/ext/image-placeholders.png
mopidy_mopify/static/js/ext/jquery.tablesorter.min.js
mopidy_mopify/static/js/ext/jquery.echonest.js
mopidy_mopify/static/js/ext/contextmenu.js
mopidy_mopify/static/js/ext/resizableColumns.js
mopidy_mopify/static/js/ext/transit.js
mopidy_mopify/static/style/style.css
mopidy_mopify/static/images/skip.png
mopidy_mopify/static/images/ajax-loader.gif
mopidy_mopify/static/images/mopify_logo.png
mopidy_mopify/static/images/thumbup.png
mopidy_mopify/static/images/buttons.png
mopidy_mopify/static/images/playerui.png
mopidy_mopify/static/images/no-album-art.jpg
mopidy_mopify/static/images/artist-placeholder.png
mopidy_mopify/static/images/searchicon.png
mopidy_mopify/static/images/thumbdown.png
mopidy_mopify/static/images/playbutton_big.png
mopidy_mopify/static/images/playbuttons-XL.png
mopidy_mopify/static/images/playbutton.png
mopidy_mopify/static/webfonts/ss-standard.js
mopidy_mopify/static/webfonts/ss-standard.ttf
mopidy_mopify/static/webfonts/ss-standard.woff
mopidy_mopify/static/webfonts/ss-standard.css
mopidy_mopify/static/webfonts/ss-standard.svg
mopidy_mopify/static/webfonts/ss-standard.eot
Mopidy_Mopify-0.1.6.dist-info/entry_points.txt
Mopidy_Mopify-0.1.6.dist-info/top_level.txt
Mopidy_Mopify-0.1.6.dist-info/DESCRIPTION.rst
Mopidy_Mopify-0.1.6.dist-info/WHEEL
Mopidy_Mopify-0.1.6.dist-info/metadata.json
Mopidy_Mopify-0.1.6.dist-info/RECORD
Mopidy_Mopify-0.1.6.dist-info/METADATA
