Metadata-Version: 2.0
Name: Mopidy-Mopify
Version: 0.1.6
Summary: A Mopidy Web client based on the (old) Spotify interface. Improved to work with spotify as main library.
Home-page: https://github.com/dirkgroenen/Mopify
Author: Dirk Groenen
Author-email: dirk@bitlabs.nl
License: GNU General Public License v3 (GPLv3)
Platform: UNKNOWN
Classifier: Environment :: No Input/Output (Daemon)
Classifier: Intended Audience :: End Users/Desktop
Classifier: License :: OSI Approved :: Apache Software License
Classifier: Operating System :: OS Independent
Classifier: Programming Language :: Python :: 2
Classifier: Topic :: Multimedia :: Sound/Audio :: Players
Requires-Dist: setuptools
Requires-Dist: Mopidy (>=0.19)
